{"cameraMode":{"drawMode":0,"name":"Shaded","section":"Shading Mode"},"sceneLighting":false,"audioPlay":false,"sceneViewState":{"m_AlwaysRefresh":true,"showFog":true,"showSkybox":false,"showFlares":true,"showImageEffects":true,"showParticleSystems":false,"showVisualEffectGraphs":true,"m_FxEnabled":true},"in2DMode":false,"pivot":{"x":6.515115261077881,"y":6.930008411407471,"z":43.69746017456055},"rotation":{"x":0.2620278596878052,"y":-0.6634752154350281,"z":0.2685483396053314,"w":0.6473389267921448},"size":10.534560203552246,"orthographic":false}